NumPlex/__init__.py
NumPlex-1.0.0.dist-info/METADATA
NumPlex-1.0.0.dist-info/WHEEL
NumPlex-1.0.0.dist-info/top_level.txt
NumPlex-1.0.0.dist-info/RECORD
